p2c/___init__.py
p2c/modelo.py
p2c-0.0.4.dist-info/LICENSE
p2c-0.0.4.dist-info/METADATA
p2c-0.0.4.dist-info/WHEEL
p2c-0.0.4.dist-info/top_level.txt
p2c-0.0.4.dist-info/RECORD
