Metadata-Version: 2.1
Name: p2c
Version: 0.0.4
Summary: paquete del proyecto 2
Author-email: Damian Leon <damianleon@usantotomas.edu.co>
License: MIT License        
Project-URL: Homepage, https://github.com/IanDam/p2c
Project-URL: Bug Tracker, https://github.com/IanDam/p2c/issues
Classifier: Programming Language :: Python :: 3
Classifier: License :: OSI Approved :: MIT License
Classifier: Operating System :: OS Independent
Requires-Python: >=3.7
License-File: LICENSE
